{
  "_class": "sharedStyle",
  "do_objectID": "F5178318-D7CE-4E62-B644-1D67ECE09D1D",
  "name": "Color / support-03",
  "value": {
    "_class": "style",
    "blur": {
      "_class": "blur",
      "center": "{0.5, 0.5}",
      "isEnabled": false,
      "motionAngle": 0,
      "radius": 7.999999523162842,
      "saturation": 1,
      "type": 0
    },
    "endMarkerType": 0,
    "fills": [
      {
        "_class": "fill",
        "color": {
          "_class": "color",
          "alpha": 1,
          "blue": 0,
          "green": 0.7568627450980392,
          "red": 0.9372549019607843
        },
        "fillType": 0,
        "isEnabled": true,
        "noiseIndex": 0,
        "noiseIntensity": 0,
        "patternFillType": 0,
        "patternTileScale": 1
      }
    ],
    "miterLimit": 10,
    "startMarkerType": 0,
    "windingRule": 1
  }
}