{
  "_class": "symbolInstance",
  "booleanOperation": 0,
  "clippingMaskMode": 0,
  "do_objectID": "1BACEF99-4574-4817-ABE8-89CDF6ECDFDB",
  "exportOptions": {
    "_class": "exportOptions",
    "do_objectID": "A9BE0AC4-4E24-4F08-AE15-F6E7419B6017",
    "exportFormats": [
    ],
    "includedLayerIds": [
    ],
    "layerOptions": 0,
    "shouldTrim": false
  },
  "frame": {
    "_class": "rect",
    "constrainProportions": false,
    "do_objectID": "1A44F224-84B8-46B2-8E54-08EC148B76B8",
    "height": 14,
    "width": 64,
    "x": 0,
    "y": 0
  },
  "hasClippingMask": false,
  "horizontalSpacing": 0,
  "isFixedToViewport": false,
  "isFlippedHorizontal": false,
  "isFlippedVertical": false,
  "isLocked": false,
  "isVisible": true,
  "layerListExpandedType": 0,
  "name": "Component/Skeleton State/Text Overlay",
  "nameIsFixed": false,
  "overrideValues": [
  ],
  "resizingConstraint": 63,
  "resizingType": 0,
  "rotation": 0,
  "scale": 1,
  "shouldBreakMaskChain": false,
  "style": {
    "_class": "style",
    "do_objectID": "4652C667-83B5-4317-9239-4A2BCEB39EE1",
    "endMarkerType": 0,
    "miterLimit": 10,
    "startMarkerType": 0,
    "windingRule": 1
  },
  "symbolID": "4CB7F7C8-8A0E-4091-804E-877723DE71F2",
  "verticalSpacing": 0
}