{
  "_class": "bitmap",
  "booleanOperation": 0,
  "clippingMask": "{{0, 0}, {1, 1}}",
  "clippingMaskMode": 0,
  "do_objectID": "57090C33-38DF-4D35-AFB7-D7D8594D0235",
  "exportOptions": {
    "_class": "exportOptions",
    "do_objectID": "61B50A91-2959-4338-9DB2-05F0CBAC7087",
    "exportFormats": [
    ],
    "includedLayerIds": [
    ],
    "layerOptions": 0,
    "shouldTrim": false
  },
  "fillReplacesImage": false,
  "frame": {
    "_class": "rect",
    "constrainProportions": true,
    "do_objectID": "54555F1E-2516-4214-B483-5CB468907686",
    "height": 250.7377049180328,
    "width": 355.0970873786408,
    "x": -12.9126213592233,
    "y": -56.55737704918033
  },
  "hasClippingMask": false,
  "image": {
    "_class": "MSJSONFileReference",
    "_ref": "images/021f81a8cec9fcebd420bbcedc37cd1b6aea22b2.png",
    "_ref_class": "MSImageData"
  },
  "intendedDPI": 0,
  "isFixedToViewport": false,
  "isFlippedHorizontal": false,
  "isFlippedVertical": false,
  "isLocked": false,
  "isVisible": true,
  "layerListExpandedType": 0,
  "name": "Bitmap",
  "nameIsFixed": false,
  "resizingConstraint": 63,
  "resizingType": 0,
  "rotation": 330,
  "shouldBreakMaskChain": false,
  "style": {
    "_class": "style",
    "do_objectID": "FA434C83-D8D2-4358-B1A5-1D3A2588109E",
    "endMarkerType": 0,
    "miterLimit": 10,
    "startMarkerType": 0,
    "windingRule": 1
  }
}