{
  "_class": "symbolInstance",
  "booleanOperation": 0,
  "clippingMaskMode": 0,
  "do_objectID": "34B23E01-6564-400C-8AB8-B1E4B571B504",
  "exportOptions": {
    "_class": "exportOptions",
    "do_objectID": "6FE9BAB9-2769-4A5F-BCA9-8DFA687FBF01",
    "exportFormats": [
    ],
    "includedLayerIds": [
    ],
    "layerOptions": 0,
    "shouldTrim": false
  },
  "frame": {
    "_class": "rect",
    "constrainProportions": false,
    "do_objectID": "8DF6DE2E-1B75-41BB-99FD-F2EAE730FB35",
    "height": 16,
    "width": 16,
    "x": 0,
    "y": 0
  },
  "hasClippingMask": false,
  "horizontalSpacing": 0,
  "isFixedToViewport": false,
  "isFlippedHorizontal": false,
  "isFlippedVertical": false,
  "isLocked": false,
  "isVisible": true,
  "layerListExpandedType": 0,
  "name": "Component/Loading/Spinner",
  "nameIsFixed": false,
  "overrideValues": [
  ],
  "resizingConstraint": 63,
  "resizingType": 0,
  "rotation": 0,
  "scale": 1,
  "shouldBreakMaskChain": false,
  "style": {
    "_class": "style",
    "do_objectID": "3137F1C8-B8C9-4424-AF8A-E5641C2237D9",
    "endMarkerType": 0,
    "miterLimit": 10,
    "startMarkerType": 0,
    "windingRule": 1
  },
  "symbolID": "D0A8B2B5-EA9C-418A-88D1-5E83EC15B390",
  "verticalSpacing": 0
}