{
  "_class": "shapeGroup",
  "booleanOperation": 0,
  "clippingMaskMode": 0,
  "do_objectID": "CB8013BC-5B29-464F-AB9B-7AC11FA9DB0A",
  "exportOptions": {
    "_class": "exportOptions",
    "do_objectID": "0B7309F4-86C0-45B8-92BE-45CB964A910F",
    "exportFormats": [
    ],
    "includedLayerIds": [
    ],
    "layerOptions": 0,
    "shouldTrim": false
  },
  "frame": {
    "_class": "rect",
    "constrainProportions": false,
    "do_objectID": "0DA66632-CD3D-4EBE-A6CF-5C0C1F0E6426",
    "height": 16,
    "width": 12,
    "x": 0,
    "y": 0
  },
  "hasClickThrough": false,
  "hasClippingMask": false,
  "isFixedToViewport": false,
  "isFlippedHorizontal": false,
  "isFlippedVertical": false,
  "isLocked": false,
  "isVisible": true,
  "layerListExpandedType": 0,
  "layers": [
    {
      "class": "shapePath",
      "id": "F76B4635-5675-4A32-A4D9-19C04D14D0BD"
    },
    {
      "class": "shapePath",
      "id": "F784B091-BCF8-467A-9712-828C61FE17D2"
    },
    {
      "class": "shapePath",
      "id": "AEFECA5C-D505-41E3-84BE-480B5C81C727"
    }
  ],
  "name": "Combined Shape",
  "nameIsFixed": false,
  "resizingConstraint": 63,
  "resizingType": 0,
  "rotation": 0,
  "shouldBreakMaskChain": false,
  "style": {
    "_class": "style",
    "do_objectID": "CCFCF033-A5E1-454D-9D6B-76FEEC8534D9",
    "endMarkerType": 0,
    "fills": [
      {
        "_class": "fill",
        "color": {
          "_class": "color",
          "alpha": 1,
          "blue": 0.6980392156862745,
          "green": 0.4392156862745099,
          "red": 0.2392156862745098
        },
        "fillType": 0,
        "isEnabled": true,
        "noiseIndex": 0,
        "noiseIntensity": 0,
        "patternFillType": 1,
        "patternTileScale": 1
      }
    ],
    "miterLimit": 10,
    "startMarkerType": 0,
    "windingRule": 0
  },
  "windingRule": 0
}