{
  "_class": "symbolInstance",
  "booleanOperation": 0,
  "clippingMaskMode": 0,
  "do_objectID": "BB16975B-157C-4309-B379-F8349446393B",
  "exportOptions": {
    "_class": "exportOptions",
    "do_objectID": "53132121-6766-4777-97FD-DFC4AA80AACE",
    "exportFormats": [
    ],
    "includedLayerIds": [
    ],
    "layerOptions": 0,
    "shouldTrim": false
  },
  "frame": {
    "_class": "rect",
    "constrainProportions": false,
    "do_objectID": "2C03BB5F-B97D-4BAB-889B-597CDC7F8A79",
    "height": 14,
    "width": 64,
    "x": 0,
    "y": 0
  },
  "hasClippingMask": false,
  "horizontalSpacing": 0,
  "isFixedToViewport": false,
  "isFlippedHorizontal": false,
  "isFlippedVertical": false,
  "isLocked": false,
  "isVisible": true,
  "layerListExpandedType": 0,
  "name": "Component/Skeleton State/Text Overlay",
  "nameIsFixed": false,
  "overrideValues": [
  ],
  "resizingConstraint": 63,
  "resizingType": 0,
  "rotation": 0,
  "scale": 1,
  "shouldBreakMaskChain": false,
  "style": {
    "_class": "style",
    "do_objectID": "FA4ED61E-782B-4E17-894A-343DA3B20B0D",
    "endMarkerType": 0,
    "miterLimit": 10,
    "startMarkerType": 0,
    "windingRule": 1
  },
  "symbolID": "4CB7F7C8-8A0E-4091-804E-877723DE71F2",
  "verticalSpacing": 0
}