{
  "_class": "shapePath",
  "booleanOperation": -1,
  "clippingMaskMode": 0,
  "do_objectID": "6D59AB67-1F59-4A04-8A81-93F641E3280B",
  "edited": true,
  "exportOptions": {
    "_class": "exportOptions",
    "do_objectID": "F5EACA17-6E64-49F9-8A56-F49F95AB9F51",
    "exportFormats": [
    ],
    "includedLayerIds": [
    ],
    "layerOptions": 0,
    "shouldTrim": false
  },
  "frame": {
    "_class": "rect",
    "constrainProportions": false,
    "do_objectID": "61E405F0-4AA9-4DA1-BF2B-F894A749C472",
    "height": 12.85199999999997,
    "width": 12.58199999999988,
    "x": 0,
    "y": 0
  },
  "hasClippingMask": false,
  "isClosed": true,
  "isFixedToViewport": false,
  "isFlippedHorizontal": false,
  "isFlippedVertical": false,
  "isLocked": false,
  "isVisible": true,
  "layerListExpandedType": 0,
  "name": "Path",
  "nameIsFixed": false,
  "pointRadiusBehaviour": 0,
  "points": [
    {
      "_class": "curvePoint",
      "cornerRadius": 0,
      "curveFrom": "{0, 1}",
      "curveMode": 1,
      "curveTo": "{0, 1}",
      "hasCurveFrom": false,
      "hasCurveTo": false,
      "point": "{0, 1}"
    },
    {
      "_class": "curvePoint",
      "cornerRadius": 0,
      "curveFrom": "{0.22746781115878875, 1}",
      "curveMode": 1,
      "curveTo": "{0.22746781115878875, 1}",
      "hasCurveFrom": false,
      "hasCurveTo": false,
      "point": "{0.22746781115878875, 1}"
    },
    {
      "_class": "curvePoint",
      "cornerRadius": 0,
      "curveFrom": "{0.30758226037195419, 0.77731092436975013}",
      "curveMode": 1,
      "curveTo": "{0.30758226037195419, 0.77731092436975013}",
      "hasCurveFrom": false,
      "hasCurveTo": false,
      "point": "{0.30758226037195419, 0.77731092436975013}"
    },
    {
      "_class": "curvePoint",
      "cornerRadius": 0,
      "curveFrom": "{0.6895565092989997, 0.77731092436975013}",
      "curveMode": 1,
      "curveTo": "{0.6895565092989997, 0.77731092436975013}",
      "hasCurveFrom": false,
      "hasCurveTo": false,
      "point": "{0.6895565092989997, 0.77731092436975013}"
    },
    {
      "_class": "curvePoint",
      "cornerRadius": 0,
      "curveFrom": "{0.76680972818311899, 1}",
      "curveMode": 1,
      "curveTo": "{0.76680972818311899, 1}",
      "hasCurveFrom": false,
      "hasCurveTo": false,
      "point": "{0.76680972818311899, 1}"
    },
    {
      "_class": "curvePoint",
      "cornerRadius": 0,
      "curveFrom": "{1, 1}",
      "curveMode": 1,
      "curveTo": "{1, 1}",
      "hasCurveFrom": false,
      "hasCurveTo": false,
      "point": "{1, 1}"
    },
    {
      "_class": "curvePoint",
      "cornerRadius": 0,
      "curveFrom": "{0.61802575107295454, 0}",
      "curveMode": 1,
      "curveTo": "{0.61802575107295454, 0}",
      "hasCurveFrom": false,
      "hasCurveTo": false,
      "point": "{0.61802575107295454, 0}"
    },
    {
      "_class": "curvePoint",
      "cornerRadius": 0,
      "curveFrom": "{0.38769670958511965, 0}",
      "curveMode": 1,
      "curveTo": "{0.38769670958511965, 0}",
      "hasCurveFrom": false,
      "hasCurveTo": false,
      "point": "{0.38769670958511965, 0}"
    }
  ],
  "resizingConstraint": 63,
  "resizingType": 0,
  "rotation": 0,
  "shouldBreakMaskChain": false,
  "style": {
    "_class": "style",
    "do_objectID": "9FE2DD76-85CD-45DE-957F-C0D817CA86B5",
    "endMarkerType": 0,
    "fills": [
      {
        "_class": "fill",
        "color": {
          "_class": "color",
          "alpha": 1,
          "blue": 0.203921568627451,
          "green": 0.1607843137254902,
          "red": 0.08235294117647059
        },
        "fillType": 0,
        "isEnabled": true,
        "noiseIndex": 0,
        "noiseIntensity": 0,
        "patternFillType": 1,
        "patternTileScale": 1
      }
    ],
    "miterLimit": 10,
    "startMarkerType": 0,
    "textStyle": {
      "_class": "textStyle",
      "do_objectID": "748CD2D1-AB33-4C49-96CC-79029A7D6F0A",
      "encodedAttributes": {
        "MSAttributedStringColorAttribute": {
          "_class": "color",
          "alpha": 1,
          "blue": 0.2039215686,
          "green": 0.1607843137,
          "red": 0.08235294118
        },
        "MSAttributedStringFontAttribute": {
          "_class": "fontDescriptor",
          "attributes": {
            "name": "HelvNeueBoldforIBM",
            "size": 18
          }
        },
        "kerning": 0,
        "paragraphStyle": {
          "_class": "paragraphStyle",
          "alignment": 0,
          "allowsDefaultTighteningForTruncation": 0,
          "baseWritingDirection": 0
        }
      },
      "verticalAlignment": 0
    },
    "windingRule": 1
  }
}