{
  "_class": "symbolInstance",
  "booleanOperation": 0,
  "clippingMaskMode": 0,
  "do_objectID": "BD6EF963-5494-4425-854F-CE8B7457E0FE",
  "exportOptions": {
    "_class": "exportOptions",
    "do_objectID": "49558C9E-369D-4444-A529-DE6B3646F293",
    "exportFormats": [
    ],
    "includedLayerIds": [
    ],
    "layerOptions": 0,
    "shouldTrim": false
  },
  "frame": {
    "_class": "rect",
    "constrainProportions": false,
    "do_objectID": "F63BE768-85B9-44CC-BFC3-127580013BC4",
    "height": 40,
    "width": 127,
    "x": 0,
    "y": 218
  },
  "hasClippingMask": false,
  "horizontalSpacing": 0,
  "isFixedToViewport": false,
  "isFlippedHorizontal": false,
  "isFlippedVertical": false,
  "isLocked": false,
  "isVisible": true,
  "layerListExpandedType": 0,
  "name": "Component/Button/Danger/Secondary/States/Disabled",
  "nameIsFixed": true,
  "overrideValues": [
  ],
  "resizingConstraint": 63,
  "resizingType": 0,
  "rotation": 0,
  "scale": 1,
  "shouldBreakMaskChain": false,
  "style": {
    "_class": "style",
    "do_objectID": "93C61E39-5CB8-425E-A082-871EEB75A397",
    "endMarkerType": 0,
    "miterLimit": 10,
    "startMarkerType": 0,
    "windingRule": 1
  },
  "symbolID": "3455AABA-3775-4F32-A5BD-5FC34DF071B0",
  "verticalSpacing": 0
}