{
  "_class": "symbolInstance",
  "booleanOperation": 0,
  "clippingMaskMode": 0,
  "do_objectID": "98CE1BE9-CBC6-4FE2-B5D2-05527B34A6E1",
  "exportOptions": {
    "_class": "exportOptions",
    "do_objectID": "B29C3A69-622A-49DF-B312-FE24F106B663",
    "exportFormats": [
    ],
    "includedLayerIds": [
    ],
    "layerOptions": 0,
    "shouldTrim": false
  },
  "frame": {
    "_class": "rect",
    "constrainProportions": false,
    "do_objectID": "905CEEB4-A788-48F0-BF8B-ED3F58EE6078",
    "height": 14,
    "width": 74,
    "x": 0,
    "y": 69
  },
  "hasClippingMask": false,
  "horizontalSpacing": 0,
  "isFixedToViewport": false,
  "isFlippedHorizontal": false,
  "isFlippedVertical": false,
  "isLocked": false,
  "isVisible": true,
  "layerListExpandedType": 0,
  "name": "Component/Skeleton State/Text",
  "nameIsFixed": false,
  "overrideValues": [
  ],
  "resizingConstraint": 63,
  "resizingType": 0,
  "rotation": 0,
  "scale": 1,
  "shouldBreakMaskChain": false,
  "style": {
    "_class": "style",
    "do_objectID": "69DC22E2-3822-494A-A658-74B97DAA3E8C",
    "endMarkerType": 0,
    "miterLimit": 10,
    "startMarkerType": 0,
    "windingRule": 1
  },
  "symbolID": "EBC14B70-6F36-4989-924D-AAF351AFE0D9",
  "verticalSpacing": 0
}