{
  "_class": "symbolInstance",
  "booleanOperation": 0,
  "clippingMaskMode": 0,
  "do_objectID": "ADFD40DC-803C-4CBA-9D4F-E15EC61B9A59",
  "exportOptions": {
    "_class": "exportOptions",
    "do_objectID": "5BC207DA-0FAD-49FA-9D2C-A6583F1B523B",
    "exportFormats": [
    ],
    "includedLayerIds": [
    ],
    "layerOptions": 0,
    "shouldTrim": false
  },
  "frame": {
    "_class": "rect",
    "constrainProportions": false,
    "do_objectID": "21BE2639-0A70-4FB3-9B7B-AC30B570BE2D",
    "height": 165,
    "width": 284,
    "x": 0,
    "y": 0
  },
  "hasClippingMask": false,
  "horizontalSpacing": 0,
  "isFixedToViewport": false,
  "isFlippedHorizontal": false,
  "isFlippedVertical": false,
  "isLocked": false,
  "isVisible": true,
  "layerListExpandedType": 0,
  "name": "Component/Tile/Selectable/Active",
  "nameIsFixed": false,
  "overrideValues": [
  ],
  "resizingConstraint": 63,
  "resizingType": 0,
  "rotation": 0,
  "scale": 1,
  "shouldBreakMaskChain": false,
  "style": {
    "_class": "style",
    "do_objectID": "06EC8566-2909-4240-9C1A-FDF00AB40542",
    "endMarkerType": 0,
    "miterLimit": 10,
    "startMarkerType": 0,
    "windingRule": 1
  },
  "symbolID": "7CA6BB1F-BED2-45EF-94A7-119626EA31F8",
  "verticalSpacing": 0
}