{
  "_class": "group",
  "booleanOperation": 0,
  "clippingMaskMode": 0,
  "do_objectID": "E0A1E577-F7E3-4908-A51A-571C77FD12AE",
  "exportOptions": {
    "_class": "exportOptions",
    "do_objectID": "63BC3EE1-962A-40A9-9052-9FFF5E9D2EB5",
    "exportFormats": [
    ],
    "includedLayerIds": [
    ],
    "layerOptions": 0,
    "shouldTrim": false
  },
  "frame": {
    "_class": "rect",
    "constrainProportions": false,
    "do_objectID": "5B06874D-AD52-4610-AB6D-6FF25C6C55CF",
    "height": 40,
    "width": 82,
    "x": 0,
    "y": 0
  },
  "hasClickThrough": false,
  "hasClippingMask": false,
  "isFixedToViewport": false,
  "isFlippedHorizontal": false,
  "isFlippedVertical": false,
  "isLocked": false,
  "isVisible": true,
  "layerListExpandedType": 2,
  "layers": [
    {
      "class": "rectangle",
      "id": "54FD6E97-A776-447C-9D81-E73113ADA678"
    }
  ],
  "name": "Structure",
  "nameIsFixed": true,
  "resizingConstraint": 63,
  "resizingType": 0,
  "rotation": 0,
  "shouldBreakMaskChain": false,
  "style": {
    "_class": "style",
    "do_objectID": "364F6B57-6F15-4D2B-AABF-EBB617C7D526",
    "endMarkerType": 0,
    "miterLimit": 10,
    "startMarkerType": 0,
    "windingRule": 1
  }
}