{
  "_class": "symbolInstance",
  "booleanOperation": 0,
  "clippingMaskMode": 0,
  "do_objectID": "4CC24807-CF21-4C7F-A5B6-2EA874073444",
  "exportOptions": {
    "_class": "exportOptions",
    "do_objectID": "797EE289-753F-437D-BA06-276AF9D3E8AC",
    "exportFormats": [
    ],
    "includedLayerIds": [
    ],
    "layerOptions": 0,
    "shouldTrim": false
  },
  "frame": {
    "_class": "rect",
    "constrainProportions": false,
    "do_objectID": "E120BCC3-D047-46C4-AAE7-2F22B6A9432F",
    "height": 14,
    "width": 94,
    "x": 0,
    "y": 191
  },
  "hasClippingMask": false,
  "horizontalSpacing": 0,
  "isFixedToViewport": false,
  "isFlippedHorizontal": false,
  "isFlippedVertical": false,
  "isLocked": false,
  "isVisible": true,
  "layerListExpandedType": 0,
  "name": "Component/Skeleton State/Text",
  "nameIsFixed": false,
  "overrideValues": [
  ],
  "resizingConstraint": 63,
  "resizingType": 0,
  "rotation": 0,
  "scale": 1,
  "shouldBreakMaskChain": false,
  "style": {
    "_class": "style",
    "do_objectID": "04BC06C1-1DA3-44BD-8E50-B49FD23A347E",
    "endMarkerType": 0,
    "miterLimit": 10,
    "startMarkerType": 0,
    "windingRule": 1
  },
  "symbolID": "EBC14B70-6F36-4989-924D-AAF351AFE0D9",
  "verticalSpacing": 0
}