{
  "_class": "shapeGroup",
  "booleanOperation": 0,
  "clippingMaskMode": 0,
  "do_objectID": "FA30CB49-A60F-4647-9A12-9811ACFEFD7D",
  "exportOptions": {
    "_class": "exportOptions",
    "do_objectID": "0FC9BBA8-D8CB-4CDB-9AA8-27658AFAD4A1",
    "exportFormats": [
    ],
    "includedLayerIds": [
    ],
    "layerOptions": 0,
    "shouldTrim": false
  },
  "frame": {
    "_class": "rect",
    "constrainProportions": false,
    "do_objectID": "2D2F204E-B28C-4949-96DD-693CC874E0CB",
    "height": 16,
    "width": 14.88099081572113,
    "x": 0,
    "y": 1.110223024625157e-16
  },
  "hasClickThrough": false,
  "hasClippingMask": false,
  "isFixedToViewport": false,
  "isFlippedHorizontal": false,
  "isFlippedVertical": false,
  "isLocked": false,
  "isVisible": true,
  "layerListExpandedType": 0,
  "layers": [
    {
      "class": "shapePath",
      "id": "66E9C9C1-E823-4EE1-9885-4DB41C58872F"
    },
    {
      "class": "shapePath",
      "id": "C519C636-FA03-43E2-A148-7EFC20538957"
    }
  ],
  "name": "Combined Shape",
  "nameIsFixed": false,
  "resizingConstraint": 63,
  "resizingType": 0,
  "rotation": 0,
  "shouldBreakMaskChain": false,
  "style": {
    "_class": "style",
    "do_objectID": "4E811F27-46CA-4430-9A54-2ECB8BF6E7B0",
    "endMarkerType": 0,
    "fills": [
      {
        "_class": "fill",
        "color": {
          "_class": "color",
          "alpha": 1,
          "blue": 0.6980392156862745,
          "green": 0.4392156862745099,
          "red": 0.2392156862745098
        },
        "fillType": 0,
        "isEnabled": true,
        "noiseIndex": 0,
        "noiseIntensity": 0,
        "patternFillType": 1,
        "patternTileScale": 1
      }
    ],
    "miterLimit": 10,
    "startMarkerType": 0,
    "windingRule": 0
  },
  "windingRule": 0
}